This XML file does not appear to have any style information associated with it. The document tree is shown below. 
<hfs_manifest>
<file_name>F.E.A.R.3.BLES00963.iso</file_name>
<file_size>13487636480</file_size>
<number_of_split_files>7</number_of_split_files>
<pieces file_size="2000000000" index="0"  url="http://github.com/freestoredrive/hostps3-iso-ef/releases/download/F.E.A.R_3/F.E.A.R.3.BLES00963_00.iso"/>
<pieces file_size="2000000000" index="1"  url="http://github.com/freestoredrive/hostps3-iso-ef/releases/download/F.E.A.R_3/F.E.A.R.3.BLES00963_01.iso"/>
<pieces file_size="2000000000" index="2"  url="http://github.com/freestoredrive/hostps3-iso-ef/releases/download/F.E.A.R_3/F.E.A.R.3.BLES00963_02.iso"/>
<pieces file_size="2000000000" index="3"  url="http://github.com/freestoredrive/hostps3-iso-ef/releases/download/F.E.A.R_3/F.E.A.R.3.BLES00963_03.iso"/>
<pieces file_size="2000000000" index="4"  url="http://github.com/freestoredrive/hostps3-iso-ef/releases/download/F.E.A.R_3/F.E.A.R.3.BLES00963_04.iso"/>
<pieces file_size="2000000000" index="5"  url="http://github.com/freestoredrive/hostps3-iso-ef/releases/download/F.E.A.R_3/F.E.A.R.3.BLES00963_05.iso"/>
<pieces file_size="1487636480" index="6"  url="http://github.com/freestoredrive/hostps3-iso-ef/releases/download/F.E.A.R_3/F.E.A.R.3.BLES00963_06.iso"/>
</hfs_manifest>
